zipfreeinfo/__init__.py
zipfreeinfo/exampleapp.py
zipfreeinfo/zipfreeinfo.py
zipfreeinfo-1.0.0.dist-info/DESCRIPTION.rst
zipfreeinfo-1.0.0.dist-info/METADATA
zipfreeinfo-1.0.0.dist-info/RECORD
zipfreeinfo-1.0.0.dist-info/WHEEL
zipfreeinfo-1.0.0.dist-info/metadata.json
zipfreeinfo-1.0.0.dist-info/top_level.txt
