Metadata-Version: 2.0
Name: zipfreeinfo
Version: 1.0.0
Summary: Provided a zip code, you are given information about that location.
Home-page: https://github.com/marcelluseasley/zipfreeinfo
Author: Marcellus Easley
Author-email: marcellus.easley@gmail.com
License: MIT license
Keywords: zipfreeinfo
Platform: UNKNOWN
Classifier: Development Status :: 2 - Pre-Alpha
Classifier: Intended Audience :: Developers
Classifier: License :: OSI Approved :: MIT License
Classifier: Natural Language :: English
Classifier: Programming Language :: Python :: 2
Classifier: Programming Language :: Python :: 2.6
Classifier: Programming Language :: Python :: 2.7
Classifier: Programming Language :: Python :: 3
Classifier: Programming Language :: Python :: 3.3
Classifier: Programming Language :: Python :: 3.4
Classifier: Programming Language :: Python :: 3.5
